[
  {
    "inputs": [
      {
        "internalType": "address",
        "name": "_worldLedger",
        "type": "address"
      },
      {
        "internalType": "address",
        "name": "_epochManager",
        "type": "address"
      },
      {
        "internalType": "address",
        "name": "_memoryFragment",
        "type": "address"
      }
    ],
    "stateMutability": "nonpayable",
    "type": "constructor"
  },
  {
    "inputs": [
      {
        "internalType": "address",
        "name": "owner",
        "type": "address"
      }
    ],
    "name": "OwnableInvalidOwner",
    "type": "error"
  },
  {
    "inputs": [
      {
        "internalType": "address",
        "name": "account",
        "type": "address"
      }
    ],
    "name": "OwnableUnauthorizedAccount",
    "type": "error"
  },
  {
    "anonymous": false,
    "inputs": [
      {
        "indexed": true,
        "internalType": "bytes32",
        "name": "npcId",
        "type": "bytes32"
      },
      {
        "indexed": true,
        "internalType": "address",
        "name": "inquirer",
        "type": "address"
      },
      {
        "indexed": false,
        "internalType": "bytes32",
        "name": "responseHash",
        "type": "bytes32"
      },
      {
        "indexed": false,
        "internalType": "uint256",
        "name": "epoch",
        "type": "uint256"
      }
    ],
    "name": "DialogueRecorded",
    "type": "event"
  },
  {
    "anonymous": false,
    "inputs": [
      {
        "indexed": true,
        "internalType": "bytes32",
        "name": "npcId",
        "type": "bytes32"
      },
      {
        "indexed": true,
        "internalType": "bytes32",
        "name": "requestId",
        "type": "bytes32"
      },
      {
        "indexed": true,
        "internalType": "address",
        "name": "inquirer",
        "type": "address"
      }
    ],
    "name": "DialogueStored",
    "type": "event"
  },
  {
    "anonymous": false,
    "inputs": [
      {
        "indexed": true,
        "internalType": "address",
        "name": "player",
        "type": "address"
      },
      {
        "indexed": true,
        "internalType": "bytes32",
        "name": "npcId",
        "type": "bytes32"
      },
      {
        "indexed": false,
        "internalType": "string",
        "name": "keyword",
        "type": "string"
      },
      {
        "indexed": false,
        "internalType": "uint256",
        "name": "fragmentId",
        "type": "uint256"
      }
    ],
    "name": "KeywordTriggered",
    "type": "event"
  },
  {
    "anonymous": false,
    "inputs": [
      {
        "indexed": true,
        "internalType": "bytes32",
        "name": "npcId",
        "type": "bytes32"
      },
      {
        "indexed": false,
        "internalType": "enum AINPC_Extended.NPCType",
        "name": "npcType",
        "type": "uint8"
      },
      {
        "indexed": false,
        "internalType": "string",
        "name": "name",
        "type": "string"
      },
      {
        "indexed": false,
        "internalType": "uint256",
        "name": "birthEpoch",
        "type": "uint256"
      }
    ],
    "name": "NPCCreated",
    "type": "event"
  },
  {
    "anonymous": false,
    "inputs": [
      {
        "indexed": true,
        "internalType": "bytes32",
        "name": "npcId",
        "type": "bytes32"
      },
      {
        "indexed": false,
        "internalType": "uint256",
        "name": "newDegradationLevel",
        "type": "uint256"
      }
    ],
    "name": "NPCDegraded",
    "type": "event"
  },
  {
    "anonymous": false,
    "inputs": [
      {
        "indexed": true,
        "internalType": "address",
        "name": "previousOwner",
        "type": "address"
      },
      {
        "indexed": true,
        "internalType": "address",
        "name": "newOwner",
        "type": "address"
      }
    ],
    "name": "OwnershipTransferred",
    "type": "event"
  },
  {
    "inputs": [
      {
        "internalType": "bytes32",
        "name": "",
        "type": "bytes32"
      }
    ],
    "name": "dialogueContents",
    "outputs": [
      {
        "internalType": "bytes32",
        "name": "requestId",
        "type": "bytes32"
      },
      {
        "internalType": "string",
        "name": "question",
        "type": "string"
      },
      {
        "internalType": "string",
        "name": "response",
        "type": "string"
      }
    ],
    "stateMutability": "view",
    "type": "function"
  },
  {
    "inputs": [
      {
        "internalType": "bytes32",
        "name": "",
        "type": "bytes32"
      },
      {
        "internalType": "uint256",
        "name": "",
        "type": "uint256"
      }
    ],
    "name": "dialogueHistory",
    "outputs": [
      {
        "internalType": "uint256",
        "name": "timestamp",
        "type": "uint256"
      },
      {
        "internalType": "address",
        "name": "inquirer",
        "type": "address"
      },
      {
        "internalType": "bytes32",
        "name": "questionHash",
        "type": "bytes32"
      },
      {
        "internalType": "bytes32",
        "name": "responseHash",
        "type": "bytes32"
      },
      {
        "internalType": "uint256",
        "name": "entropyLevel",
        "type": "uint256"
      },
      {
        "internalType": "uint256",
        "name": "epoch",
        "type": "uint256"
      }
    ],
    "stateMutability": "view",
    "type": "function"
  },
  {
    "inputs": [],
    "name": "epochManager",
    "outputs": [
      {
        "internalType": "contract EpochManager",
        "name": "",
        "type": "address"
      }
    ],
    "stateMutability": "view",
    "type": "function"
  },
  {
    "inputs": [],
    "name": "getAllKeywords",
    "outputs": [
      {
        "internalType": "string[]",
        "name": "",
        "type": "string[]"
      }
    ],
    "stateMutability": "view",
    "type": "function"
  },
  {
    "inputs": [],
    "name": "getAllNPCs",
    "outputs": [
      {
        "internalType": "bytes32[]",
        "name": "",
        "type": "bytes32[]"
      }
    ],
    "stateMutability": "view",
    "type": "function"
  },
  {
    "inputs": [
      {
        "internalType": "bytes32",
        "name": "npcId",
        "type": "bytes32"
      }
    ],
    "name": "getDialogueCount",
    "outputs": [
      {
        "internalType": "uint256",
        "name": "",
        "type": "uint256"
      }
    ],
    "stateMutability": "view",
    "type": "function"
  },
  {
    "inputs": [
      {
        "internalType": "bytes32",
        "name": "npcId",
        "type": "bytes32"
      }
    ],
    "name": "getDialogueHistory",
    "outputs": [
      {
        "components": [
          {
            "internalType": "uint256",
            "name": "timestamp",
            "type": "uint256"
          },
          {
            "internalType": "address",
            "name": "inquirer",
            "type": "address"
          },
          {
            "internalType": "bytes32",
            "name": "questionHash",
            "type": "bytes32"
          },
          {
            "internalType": "bytes32",
            "name": "responseHash",
            "type": "bytes32"
          },
          {
            "internalType": "uint256",
            "name": "entropyLevel",
            "type": "uint256"
          },
          {
            "internalType": "uint256",
            "name": "epoch",
            "type": "uint256"
          }
        ],
        "internalType": "struct AINPC_Extended.Dialogue[]",
        "name": "",
        "type": "tuple[]"
      }
    ],
    "stateMutability": "view",
    "type": "function"
  },
  {
    "inputs": [
      {
        "internalType": "string",
        "name": "keyword",
        "type": "string"
      }
    ],
    "name": "getKeywordTrigger",
    "outputs": [
      {
        "components": [
          {
            "internalType": "string",
            "name": "keyword",
            "type": "string"
          },
          {
            "internalType": "uint256",
            "name": "fragmentId",
            "type": "uint256"
          },
          {
            "internalType": "bytes32",
            "name": "npcId",
            "type": "bytes32"
          },
          {
            "internalType": "uint256",
            "name": "epoch",
            "type": "uint256"
          },
          {
            "internalType": "bool",
            "name": "isActive",
            "type": "bool"
          }
        ],
        "internalType": "struct AINPC_Extended.KeywordTrigger",
        "name": "",
        "type": "tuple"
      }
    ],
    "stateMutability": "view",
    "type": "function"
  },
  {
    "inputs": [
      {
        "internalType": "bytes32",
        "name": "npcId",
        "type": "bytes32"
      }
    ],
    "name": "getNPC",
    "outputs": [
      {
        "components": [
          {
            "internalType": "bytes32",
            "name": "idHash",
            "type": "bytes32"
          },
          {
            "internalType": "enum AINPC_Extended.NPCType",
            "name": "npcType",
            "type": "uint8"
          },
          {
            "internalType": "string",
            "name": "name",
            "type": "string"
          },
          {
            "internalType": "string",
            "name": "description",
            "type": "string"
          },
          {
            "internalType": "uint256",
            "name": "creationTime",
            "type": "uint256"
          },
          {
            "internalType": "uint256",
            "name": "interactionCount",
            "type": "uint256"
          },
          {
            "internalType": "uint256",
            "name": "degradationLevel",
            "type": "uint256"
          },
          {
            "internalType": "uint256",
            "name": "birthEpoch",
            "type": "uint256"
          },
          {
            "internalType": "bool",
            "name": "isActive",
            "type": "bool"
          }
        ],
        "internalType": "struct AINPC_Extended.NPC",
        "name": "",
        "type": "tuple"
      }
    ],
    "stateMutability": "view",
    "type": "function"
  },
  {
    "inputs": [
      {
        "internalType": "enum AINPC_Extended.NPCType",
        "name": "npcType",
        "type": "uint8"
      }
    ],
    "name": "getNPCByType",
    "outputs": [
      {
        "internalType": "bytes32[]",
        "name": "",
        "type": "bytes32[]"
      }
    ],
    "stateMutability": "view",
    "type": "function"
  },
  {
    "inputs": [
      {
        "internalType": "bytes32",
        "name": "npcId",
        "type": "bytes32"
      },
      {
        "internalType": "address",
        "name": "player",
        "type": "address"
      }
    ],
    "name": "getNPCEpochState",
    "outputs": [
      {
        "internalType": "bool",
        "name": "exists",
        "type": "bool"
      },
      {
        "internalType": "string",
        "name": "stateDescription",
        "type": "string"
      }
    ],
    "stateMutability": "view",
    "type": "function"
  },
  {
    "inputs": [
      {
        "internalType": "address",
        "name": "player",
        "type": "address"
      }
    ],
    "name": "getPlayerInteractionCount",
    "outputs": [
      {
        "internalType": "uint256",
        "name": "",
        "type": "uint256"
      }
    ],
    "stateMutability": "view",
    "type": "function"
  },
  {
    "inputs": [
      {
        "internalType": "bytes32",
        "name": "npcId",
        "type": "bytes32"
      },
      {
        "internalType": "bytes32",
        "name": "questionHash",
        "type": "bytes32"
      }
    ],
    "name": "interact",
    "outputs": [
      {
        "internalType": "bytes32",
        "name": "responseRequestId",
        "type": "bytes32"
      }
    ],
    "stateMutability": "nonpayable",
    "type": "function"
  },
  {
    "inputs": [
      {
        "internalType": "string",
        "name": "",
        "type": "string"
      }
    ],
    "name": "keywordTriggers",
    "outputs": [
      {
        "internalType": "string",
        "name": "keyword",
        "type": "string"
      },
      {
        "internalType": "uint256",
        "name": "fragmentId",
        "type": "uint256"
      },
      {
        "internalType": "bytes32",
        "name": "npcId",
        "type": "bytes32"
      },
      {
        "internalType": "uint256",
        "name": "epoch",
        "type": "uint256"
      },
      {
        "internalType": "bool",
        "name": "isActive",
        "type": "bool"
      }
    ],
    "stateMutability": "view",
    "type": "function"
  },
  {
    "inputs": [
      {
        "internalType": "uint256",
        "name": "",
        "type": "uint256"
      }
    ],
    "name": "keywords",
    "outputs": [
      {
        "internalType": "string",
        "name": "",
        "type": "string"
      }
    ],
    "stateMutability": "view",
    "type": "function"
  },
  {
    "inputs": [],
    "name": "memoryFragment",
    "outputs": [
      {
        "internalType": "contract MemoryFragment",
        "name": "",
        "type": "address"
      }
    ],
    "stateMutability": "view",
    "type": "function"
  },
  {
    "inputs": [
      {
        "internalType": "uint256",
        "name": "",
        "type": "uint256"
      }
    ],
    "name": "npcIds",
    "outputs": [
      {
        "internalType": "bytes32",
        "name": "",
        "type": "bytes32"
      }
    ],
    "stateMutability": "view",
    "type": "function"
  },
  {
    "inputs": [
      {
        "internalType": "bytes32",
        "name": "",
        "type": "bytes32"
      }
    ],
    "name": "npcs",
    "outputs": [
      {
        "internalType": "bytes32",
        "name": "idHash",
        "type": "bytes32"
      },
      {
        "internalType": "enum AINPC_Extended.NPCType",
        "name": "npcType",
        "type": "uint8"
      },
      {
        "internalType": "string",
        "name": "name",
        "type": "string"
      },
      {
        "internalType": "string",
        "name": "description",
        "type": "string"
      },
      {
        "internalType": "uint256",
        "name": "creationTime",
        "type": "uint256"
      },
      {
        "internalType": "uint256",
        "name": "interactionCount",
        "type": "uint256"
      },
      {
        "internalType": "uint256",
        "name": "degradationLevel",
        "type": "uint256"
      },
      {
        "internalType": "uint256",
        "name": "birthEpoch",
        "type": "uint256"
      },
      {
        "internalType": "bool",
        "name": "isActive",
        "type": "bool"
      }
    ],
    "stateMutability": "view",
    "type": "function"
  },
  {
    "inputs": [],
    "name": "owner",
    "outputs": [
      {
        "internalType": "address",
        "name": "",
        "type": "address"
      }
    ],
    "stateMutability": "view",
    "type": "function"
  },
  {
    "inputs": [
      {
        "internalType": "address",
        "name": "",
        "type": "address"
      }
    ],
    "name": "playerInteractionCount",
    "outputs": [
      {
        "internalType": "uint256",
        "name": "",
        "type": "uint256"
      }
    ],
    "stateMutability": "view",
    "type": "function"
  },
  {
    "inputs": [],
    "name": "renounceOwnership",
    "outputs": [],
    "stateMutability": "nonpayable",
    "type": "function"
  },
  {
    "inputs": [
      {
        "internalType": "bytes32",
        "name": "npcId",
        "type": "bytes32"
      },
      {
        "internalType": "bytes32",
        "name": "requestId",
        "type": "bytes32"
      },
      {
        "internalType": "bytes32",
        "name": "questionHash",
        "type": "bytes32"
      },
      {
        "internalType": "string",
        "name": "questionText",
        "type": "string"
      },
      {
        "internalType": "string",
        "name": "responseText",
        "type": "string"
      }
    ],
    "name": "storeDialogue",
    "outputs": [],
    "stateMutability": "nonpayable",
    "type": "function"
  },
  {
    "inputs": [
      {
        "internalType": "address",
        "name": "newOwner",
        "type": "address"
      }
    ],
    "name": "transferOwnership",
    "outputs": [],
    "stateMutability": "nonpayable",
    "type": "function"
  },
  {
    "inputs": [
      {
        "internalType": "address",
        "name": "player",
        "type": "address"
      },
      {
        "internalType": "string",
        "name": "keyword",
        "type": "string"
      },
      {
        "internalType": "bytes32",
        "name": "npcId",
        "type": "bytes32"
      }
    ],
    "name": "triggerKeywordReward",
    "outputs": [],
    "stateMutability": "nonpayable",
    "type": "function"
  },
  {
    "inputs": [],
    "name": "worldLedger",
    "outputs": [
      {
        "internalType": "contract WorldLedger",
        "name": "",
        "type": "address"
      }
    ],
    "stateMutability": "view",
    "type": "function"
  }
]